indexedtar/__init__.py
indexedtar/itar.py
indexedtar-1.0.1.dist-info/LICENSE
indexedtar-1.0.1.dist-info/METADATA
indexedtar-1.0.1.dist-info/WHEEL
indexedtar-1.0.1.dist-info/entry_points.txt
indexedtar-1.0.1.dist-info/top_level.txt
indexedtar-1.0.1.dist-info/RECORD
