Metadata-Version: 2.1
Name: indexedtar
Version: 1.0.1
Summary: build/search/extract_from uncompressed indexed tar archives for fast random access. The index is in the tar itself.
Home-page: https://github.com/colon3ltocard/pyindexedtar
Author: Frank Guibert
Author-email: frank.guibert.work@gmail.com
License: MIT
Keywords: tar,indexed,archives
Platform: UNKNOWN
Requires-Python: >=3.8
